resim/ros2/resim_log_from_ros2_python.pyi
resim.libs/ament/lib/librosbag2_storage_default_plugins.so
resim.libs/ament/lib/librosbag2_storage_mcap_plugin.so
resim.libs/ament/manifest.txt
resim.libs/ament/share/action_msgs/msg/GoalInfo.msg
resim.libs/ament/share/action_msgs/msg/GoalStatus.msg
resim.libs/ament/share/action_msgs/msg/GoalStatusArray.msg
resim.libs/ament/share/ament_index/resource_index/packages/action_msgs/package.xml
resim.libs/ament/share/ament_index/resource_index/packages/builtin_interfaces/package.xml
resim.libs/ament/share/ament_index/resource_index/packages/geometry_msgs/package.xml
resim.libs/ament/share/ament_index/resource_index/packages/nav_msgs/package.xml
resim.libs/ament/share/ament_index/resource_index/packages/rcl_interfaces/package.xml
resim.libs/ament/share/ament_index/resource_index/packages/rmw_dds_common/package.xml
resim.libs/ament/share/ament_index/resource_index/packages/rosbag2_storage/package.xml
resim.libs/ament/share/ament_index/resource_index/packages/rosbag2_storage_plugins/package.xml
resim.libs/ament/share/ament_index/resource_index/packages/rosbag2_storage_plugins/rosbag2_storage_default_plugins_plugins.xml
resim.libs/ament/share/ament_index/resource_index/packages/rosbag2_storage_plugins/rosbag2_storage_mcap_plugin_plugins.xml
resim.libs/ament/share/ament_index/resource_index/packages/rosgraph_msgs/package.xml
resim.libs/ament/share/ament_index/resource_index/packages/sensor_msgs/package.xml
resim.libs/ament/share/ament_index/resource_index/packages/statistics_msgs/package.xml
resim.libs/ament/share/ament_index/resource_index/packages/std_msgs/package.xml
resim.libs/ament/share/ament_index/resource_index/packages/tf2_msgs/package.xml
resim.libs/ament/share/ament_index/resource_index/packages/unique_identifier_msgs/package.xml
resim.libs/ament/share/ament_index/resource_index/packages/vision_msgs/package.xml
resim_ros2-0.0.0.dist-info/WHEEL
resim_ros2-0.0.0.dist-info/METADATA
resim_ros2-0.0.0.dist-info/RECORD
